vd_proto/amino/amino_pb2.py
vd_proto/amino/amino_pb2.pyi
vd_proto/amino/amino_pb2_grpc.py
vd_proto/cosmos/app/runtime/v1alpha1/module_pb2.py
vd_proto/cosmos/app/runtime/v1alpha1/module_pb2.pyi
vd_proto/cosmos/app/runtime/v1alpha1/module_pb2_grpc.py
vd_proto/cosmos/app/v1alpha1/config_pb2.py
vd_proto/cosmos/app/v1alpha1/config_pb2.pyi
vd_proto/cosmos/app/v1alpha1/config_pb2_grpc.py
vd_proto/cosmos/app/v1alpha1/module_pb2.py
vd_proto/cosmos/app/v1alpha1/module_pb2.pyi
vd_proto/cosmos/app/v1alpha1/module_pb2_grpc.py
vd_proto/cosmos/app/v1alpha1/query_pb2.py
vd_proto/cosmos/app/v1alpha1/query_pb2.pyi
vd_proto/cosmos/app/v1alpha1/query_pb2_grpc.py
vd_proto/cosmos/auth/module/v1/module_pb2.py
vd_proto/cosmos/auth/module/v1/module_pb2.pyi
vd_proto/cosmos/auth/module/v1/module_pb2_grpc.py
vd_proto/cosmos/auth/v1beta1/auth_pb2.py
vd_proto/cosmos/auth/v1beta1/auth_pb2.pyi
vd_proto/cosmos/auth/v1beta1/auth_pb2_grpc.py
vd_proto/cosmos/auth/v1beta1/genesis_pb2.py
vd_proto/cosmos/auth/v1beta1/genesis_pb2.pyi
vd_proto/cosmos/auth/v1beta1/genesis_pb2_grpc.py
vd_proto/cosmos/auth/v1beta1/query_pb2.py
vd_proto/cosmos/auth/v1beta1/query_pb2.pyi
vd_proto/cosmos/auth/v1beta1/query_pb2_grpc.py
vd_proto/cosmos/auth/v1beta1/tx_pb2.py
vd_proto/cosmos/auth/v1beta1/tx_pb2.pyi
vd_proto/cosmos/auth/v1beta1/tx_pb2_grpc.py
vd_proto/cosmos/authz/module/v1/module_pb2.py
vd_proto/cosmos/authz/module/v1/module_pb2.pyi
vd_proto/cosmos/authz/module/v1/module_pb2_grpc.py
vd_proto/cosmos/authz/v1beta1/authz_pb2.py
vd_proto/cosmos/authz/v1beta1/authz_pb2.pyi
vd_proto/cosmos/authz/v1beta1/authz_pb2_grpc.py
vd_proto/cosmos/authz/v1beta1/event_pb2.py
vd_proto/cosmos/authz/v1beta1/event_pb2.pyi
vd_proto/cosmos/authz/v1beta1/event_pb2_grpc.py
vd_proto/cosmos/authz/v1beta1/genesis_pb2.py
vd_proto/cosmos/authz/v1beta1/genesis_pb2.pyi
vd_proto/cosmos/authz/v1beta1/genesis_pb2_grpc.py
vd_proto/cosmos/authz/v1beta1/query_pb2.py
vd_proto/cosmos/authz/v1beta1/query_pb2.pyi
vd_proto-0.0.0.dist-info/METADATA
vd_proto-0.0.0.dist-info/WHEEL
vd_proto-0.0.0.dist-info/top_level.txt
vd_proto-0.0.0.dist-info/RECORD
