Metadata-Version: 2.4
Name: vd-proto
Version: 0.0.0
Summary: Protos for Vindax Chain protocol
Author: Vindax Trading Inc.
Author-email: contact@vindax.exchange
Requires-Python: >=3.8
Requires-Dist: protobuf>=4.23
Requires-Dist: grpcio-tools>=1.54
Requires-Dist: grpcio>=1.54
Dynamic: author
Dynamic: author-email
Dynamic: requires-dist
Dynamic: requires-python
Dynamic: summary
